api/__init__.py
api/admin.py
api/apps.py
api/models.py
api/tests.py
api/tornado.py
api/url.py
api/urls.py
api/views.py
api/migrations/0001_initial.py
api/migrations/__init__.py
data_base/__init__.py
data_base/main.py
models/__init__.py
models/user.py
my_fastapi_app/__init__.py
my_fastapi_app/main.py
my_fastapi_app/routers/__init__.py
my_fastapi_app/routers/items.py
myproject/__init__.py
myproject/asgi.py
myproject/email_test.py
myproject/file.py
myproject/forkUtil.py
myproject/log.py
myproject/logging_config.py
myproject/middleware.py
myproject/requests_test.py
myproject/settings.py
myproject/urls.py
myproject/wsgi.py
tool_net-1.0.0.dist-info/LICENSE
tool_net-1.0.0.dist-info/METADATA
tool_net-1.0.0.dist-info/WHEEL
tool_net-1.0.0.dist-info/top_level.txt
tool_net-1.0.0.dist-info/RECORD
