Metadata-Version: 2.1
Name: tool_net
Version: 1.0.0
Summary: 一个在线工具
Home-page: https://github.com/TungTJD/personage_net.git
Author: tangjiadong
Author-email: 958999498@qq.com
Classifier: Programming Language :: Python :: 3
Classifier: License :: OSI Approved :: MIT License
Classifier: Operating System :: OS Independent
Requires-Python: >=3.12
License-File: LICENSE
Requires-Dist: aiomysql ==0.2.0
Requires-Dist: annotated-types ==0.7.0
Requires-Dist: anyio ==4.4.0
Requires-Dist: asgiref ==3.8.1
Requires-Dist: certifi ==2024.6.2
Requires-Dist: chardet ==5.2.0
Requires-Dist: charset-normalizer ==3.3.2
Requires-Dist: click ==8.1.7
Requires-Dist: colorama ==0.4.6
Requires-Dist: configparser ==7.0.0
Requires-Dist: Django ==5.0.6
Requires-Dist: dnspython ==2.6.1
Requires-Dist: email-validator ==2.2.0
Requires-Dist: fastapi ==0.111.0
Requires-Dist: fastapi-cli ==0.0.4
Requires-Dist: h11 ==0.14.0
Requires-Dist: httpcore ==1.0.5
Requires-Dist: httptools ==0.6.1
Requires-Dist: httpx ==0.27.0
Requires-Dist: idna ==3.7
Requires-Dist: importlib-metadata ==7.1.0
Requires-Dist: Jinja2 ==3.1.4
Requires-Dist: Markdown ==3.6
Requires-Dist: markdown-it-py ==3.0.0
Requires-Dist: MarkupSafe ==2.1.5
Requires-Dist: mdurl ==0.1.2
Requires-Dist: mysqlclient ==2.2.4
Requires-Dist: orjson ==3.10.5
Requires-Dist: psutil ==6.0.0
Requires-Dist: pydantic ==2.7.4
Requires-Dist: pydantic-core ==2.18.4
Requires-Dist: Pygments ==2.18.0
Requires-Dist: PyJWT ==2.8.0
Requires-Dist: PyMySQL ==1.1.1
Requires-Dist: python-dotenv ==1.0.1
Requires-Dist: python-multipart ==0.0.9
Requires-Dist: PyYAML ==6.0.1
Requires-Dist: requests ==2.32.3
Requires-Dist: rich ==13.7.1
Requires-Dist: setuptools ==70.0.0
Requires-Dist: shellingham ==1.5.4
Requires-Dist: sniffio ==1.3.1
Requires-Dist: soupsieve ==2.5
Requires-Dist: sqlparse ==0.5.0
Requires-Dist: starlette ==0.37.2
Requires-Dist: tornado ==6.4.1
Requires-Dist: typer ==0.12.3
Requires-Dist: typing-extensions ==4.12.2
Requires-Dist: tzdata ==2024.1
Requires-Dist: ujson ==5.10.0
Requires-Dist: urllib3 ==2.2.1
Requires-Dist: uvicorn ==0.30.1
Requires-Dist: watchfiles ==0.22.0
Requires-Dist: websockets ==12.0
Requires-Dist: wheel ==0.43.0
Requires-Dist: zipp ==3.19.2
